[
{
  "name":"Río Guejar",
  "shortDescription":"Maravilla natural. Ecoturismo",
  "review":"4/5",
  "image":"@drawable/guejar"
},
{
  "name":"Caño Cristales",
  "shortDescription":"Maravilla natural. Ecoturismo",
  "review":"5/5",
  "image":"@drawable/cristales"
},
{
  "name":"Ombligo de Colombia",
  "shortDescription":"Sitio de interés. Turismo cultural",
  "review":"3/5",
  "image":"@drawable/ombligo"
},
  {
    "name":"Termales del Ruiz",
    "shortDescription":"Termales Volcánicos. Ecoturismo",
    "review":"5/5",
    "image":"@drawable/termalesdelruiz"
  },
  {
    "name":"Nevado del Ruiz",
    "shortDescription":"Maravilla natural. Ecoturismo",
    "review":"5/5",
    "image":"@drawable/nevado"
  },
  {
    "name":"Parque del Café",
    "shortDescription":"Parque de atracciones temático. Turismo cultural",
    "review":"5/5",
    "image":"@drawable/parquedelcafe"
  },
  {
    "name":"Tibasosa",
    "shortDescription":"Parque de atracciones extremas. Turismo extremo",
    "review":"5/5",
    "image":"@drawable/tibasosa"
  },
  {
    "name":"Villa de Leyva",
    "shortDescription":"Museos  y sitios de Interes. Turismo cultural",
    "review":"5/5",
    "image":"@drawable/villa"
  },
  {
    "name":"Mongui",
    "shortDescription":"Fabrica de Balones. Turismo cultural",
    "review":"5/5",
    "image":"@drawable/mongi"
  },
  {
    "name":"Monserrate",
    "shortDescription":"Altura y fe de la capital",
    "review":"5/5",
    "image":"@drawable/monserrat"
  },
  {
    "name":"Maloka",
    "shortDescription":"Museo interactivo de ciencia y tecnologia",
    "review":"5/5",
    "image":"@drawable/maloka"
  },
  {
    "name":"Parque simon Bolivar",
    "shortDescription":"Parque urbano y pulmon de Bogota",
    "review":"5/5",
    "image":"@drawable/simon"
  }





]
